aegis_ai/.gitignore
aegis_ai/__init__.py
aegis_ai/_version.py
aegis_ai/data_models.py
aegis_ai/prompt.py
aegis_ai/agents/__init__.py
aegis_ai/agents/safety.py
aegis_ai/features/__init__.py
aegis_ai/features/data_models.py
aegis_ai/features/component/__init__.py
aegis_ai/features/component/data_models.py
aegis_ai/features/cve/__init__.py
aegis_ai/features/cve/data_models.py
aegis_ai/toolsets/__init__.py
aegis_ai/toolsets/tools/__init__.py
aegis_ai/toolsets/tools/cisakev/__init__.py
aegis_ai/toolsets/tools/cwe/__init__.py
aegis_ai/toolsets/tools/cwe/data_models.py
aegis_ai/toolsets/tools/kernel_cves/__init__.py
aegis_ai/toolsets/tools/osidb/__init__.py
aegis_ai/toolsets/tools/osidb/osidb_client.py
aegis_ai/toolsets/tools/osvdev/__init__.py
aegis_ai/toolsets/tools/wikipedia/__init__.py
aegis_ai_cli/README.md
aegis_ai_cli/__init__.py
aegis_ai_cli/main.py
aegis_ai_ml/README.md
aegis_ai_ml/etc/normalize_text-example.txt
aegis_ai_ml/src/osidb_retrieve.py
aegis_ai_ml/src/classifier/secbert_fine_tuning.py
aegis_ai_ml/src/classifier/kernel-cve-impact-classifier/.gitignore
aegis_ai_ml/src/classifier/kernel-cve-impact-classifier/README.md
aegis_ai_ml/src/classifier/kernel-cve-impact-classifier/cve_data_scraper.py
aegis_ai_ml/src/classifier/kernel-cve-impact-classifier/cve_feature_extraction.py
aegis_ai_ml/src/classifier/kernel-cve-impact-classifier/cve_predictor.py
aegis_ai_ml/src/classifier/kernel-cve-impact-classifier/cve_smote_balancer.py
aegis_ai_ml/src/classifier/kernel-cve-impact-classifier/split_datasets_for_train_test.py
aegis_ai_ml/src/classifier/kernel-cve-impact-classifier/test_cve_model.py
aegis_ai_ml/src/classifier/kernel-cve-impact-classifier/xgboost_train.py
aegis_ai_ml/src/classifier/kernel-cve-impact-classifier/data/README.md
aegis_ai_ml/src/classifier/kernel-cve-impact-classifier/data/balanced-training-dataset-through-smote.csv
aegis_ai_ml/src/classifier/kernel-cve-impact-classifier/data/cve_analysis_report.json
aegis_ai-0.5.1.dist-info/METADATA
aegis_ai-0.5.1.dist-info/WHEEL
aegis_ai-0.5.1.dist-info/entry_points.txt
aegis_ai-0.5.1.dist-info/licenses/LICENSE
aegis_ai-0.5.1.dist-info/RECORD
