Metadata-Version: 2.4
Name: aegis-ai
Version: 0.5.1
Summary: Perform security analysis on security artifacts.
Project-URL: Homepage, https://github.com/RedHatProductSecurity/aegis-ai
Project-URL: Documentation, https://github.com/RedHatProductSecurity/aegis-ai/tree/main/README.md
Project-URL: Changelog, https://github.com/RedHatProductSecurity/aegis-ai/blob/main/docs/CHANGELOG.md
Project-URL: Issues, https://github.com/RedHatProductSecurity/aegis-ai/issues
Author-email: James Fuller <jfuller@redhat.com>
License-File: LICENSE
Classifier: License :: OSI Approved :: MIT License
Classifier: Programming Language :: Python :: 3
Classifier: Programming Language :: Python :: 3.13
Classifier: Topic :: Security
Requires-Python: >=3.13
Requires-Dist: aiofiles>=25.1.0
Requires-Dist: aiohttp>=3.13.2
Requires-Dist: cisa-kev>=2.0.2
Requires-Dist: click-completion>=0.5.2
Requires-Dist: click>=8.2.1
Requires-Dist: cvss>=3.4
Requires-Dist: dotenv>=0.9.9
Requires-Dist: fastapi-gssapi>=0.1.1
Requires-Dist: fastapi>=0.121.1
Requires-Dist: httpx>=0.28.1
Requires-Dist: jinja2>=3.1.6
Requires-Dist: logfire[fastapi,httpx,sqlite3]
Requires-Dist: mcp-nvd>=0.0.1
Requires-Dist: mcp-pypi>=2.7.1
Requires-Dist: numpy>=2.3.3
Requires-Dist: osidb-bindings>=5.0.0
Requires-Dist: packageurl-python>=0.16.0
Requires-Dist: platformdirs>=4.3.8
Requires-Dist: pydantic-ai-slim[anthropic,duckduckgo,google,mcp,openai,tavily]>=1.20.0
Requires-Dist: pydantic-evals>=1.20.0
Requires-Dist: pydantic>=2.12.4
Requires-Dist: pygithub>=2.7.0
Requires-Dist: requests-gssapi>=1.4.0
Requires-Dist: rich>=14.0.0
Requires-Dist: uv>=0.9.8
Requires-Dist: uvicorn[standard]>=0.38.0
Requires-Dist: wikipedia-mcp>=1.5.8
Requires-Dist: wikipedia>=1.4.0
Provides-Extra: ml-deps
Requires-Dist: accelerate>=0.20.0; extra == 'ml-deps'
Requires-Dist: datasets>=2.0.0; extra == 'ml-deps'
Requires-Dist: huggingface-hub>=0.8.0; extra == 'ml-deps'
Requires-Dist: imbalanced-learn>=0.13.0; extra == 'ml-deps'
Requires-Dist: matplotlib>=3.10.5; extra == 'ml-deps'
Requires-Dist: numpy>=2.3.2; extra == 'ml-deps'
Requires-Dist: pandas>=1.5.0; extra == 'ml-deps'
Requires-Dist: scikit-learn>=1.1.0; extra == 'ml-deps'
Requires-Dist: seaborn>=0.13.2; extra == 'ml-deps'
Requires-Dist: torch>=1.9.0; extra == 'ml-deps'
Requires-Dist: tqdm>=4.60.0; extra == 'ml-deps'
Requires-Dist: transformers>=4.20.0; extra == 'ml-deps'
Requires-Dist: xgboost>=1.7.0; extra == 'ml-deps'
